utilmeta_proxy/__init__.py
utilmeta_proxy/__main__.py
utilmeta_proxy/main.py
utilmeta_proxy/meta.ini
utilmeta_proxy/bin/__init__.py
utilmeta_proxy/bin/cmd.py
utilmeta_proxy/bin/setup.py
utilmeta_proxy/bin/scripts/install-mysql-rhel.sh
utilmeta_proxy/bin/scripts/setup-mysql.sh
utilmeta_proxy/bin/scripts/setup-nginx.sh
utilmeta_proxy/bin/scripts/setup-postgresql.sh
utilmeta_proxy/config/__init__.py
utilmeta_proxy/config/conf.py
utilmeta_proxy/config/env.py
utilmeta_proxy/config/service.py
utilmeta_proxy/domain/__init__.py
utilmeta_proxy/domain/service/__init__.py
utilmeta_proxy/domain/service/api.py
utilmeta_proxy/domain/service/models.py
utilmeta_proxy/domain/service/schema.py
utilmeta_proxy/domain/service/migrations/0001_initial.py
utilmeta_proxy/domain/service/migrations/__init__.py
utilmeta_proxy/service/__init__.py
utilmeta_proxy/service/api.py
utilmeta_proxy/service/connect.py
utilmeta_proxy/service/monitor/__init__.py
utilmeta_proxy/service/proxy/__init__.py
utilmeta_proxy/service/proxy/api.py
utilmeta_proxy-0.1.2.dist-info/METADATA
utilmeta_proxy-0.1.2.dist-info/WHEEL
utilmeta_proxy-0.1.2.dist-info/entry_points.txt
utilmeta_proxy-0.1.2.dist-info/licenses/LICENSE
utilmeta_proxy-0.1.2.dist-info/RECORD
